as1170/__init__.py
as1170/driver.py
as1170_python-1.0.2.dist-info/licenses/LICENSE
as1170_python-1.0.2.dist-info/METADATA
as1170_python-1.0.2.dist-info/WHEEL
as1170_python-1.0.2.dist-info/entry_points.txt
as1170_python-1.0.2.dist-info/top_level.txt
as1170_python-1.0.2.dist-info/RECORD
