Metadata-Version: 2.4
Name: AS1170-Python
Version: 1.0.2
Summary: Library to control with python the AS1170 Led driver with I2C and a Strobe GPIO Pin
Home-page: https://github.com/SupernovaIndustries/AS1170-Python
Author: Alessandro Cursoli
Author-email: Alessandro Cursoli <alessandro.cursoli@supernovaindustries.it>
License: MIT
Project-URL: Homepage, https://github.com/SupernovaIndustries/AS1170-Python
Project-URL: Repository, https://github.com/SupernovaIndustries/AS1170-Python
Classifier: Programming Language :: Python :: 3
Classifier: License :: OSI Approved :: MIT License
Classifier: Operating System :: POSIX :: Linux
Requires-Python: >=3.6
License-File: LICENSE
Requires-Dist: smbus2
Requires-Dist: RPi.GPIO
Dynamic: author
Dynamic: home-page
Dynamic: license-file
Dynamic: requires-python
